LICENSE
MANIFEST.in
README.rst
setup.py
docs/Makefile
docs/source/conf.py
docs/source/example.py
docs/source/index.rst
sphinx_nameko_theme/__init__.py
sphinx_nameko_theme/__init__.pyc
sphinx_nameko_theme.egg-info/PKG-INFO
sphinx_nameko_theme.egg-info/SOURCES.txt
sphinx_nameko_theme.egg-info/dependency_links.txt
sphinx_nameko_theme.egg-info/entry_points.txt
sphinx_nameko_theme.egg-info/not-zip-safe
sphinx_nameko_theme.egg-info/requires.txt
sphinx_nameko_theme.egg-info/top_level.txt
sphinx_nameko_theme/nameko/layout.html
sphinx_nameko_theme/nameko/reference.html
sphinx_nameko_theme/nameko/relations.html
sphinx_nameko_theme/nameko/theme.conf
sphinx_nameko_theme/nameko/static/nameko.css_t
sphinx_nameko_theme/nameko/static/pygments.css