Metadata-Version: 1.1
Name: sphinx-nameko-theme
Version: 0.0.3
Summary: Sphinx Nameko Theme
Home-page: https://github.com/onefinestay/sphinx-nameko-theme
Author: onefinestay
Author-email: nameko-devs@onefinestay.com
License: MIT
Platform: UNKNOWN
Classifier: Intended Audience :: Developers
Classifier: License :: OSI Approved :: MIT License
Classifier: Natural Language :: English
Classifier: Operating System :: OS Independent
Classifier: Programming Language :: Python
Classifier: Topic :: Internet
Classifier: Topic :: Software Development :: Documentation
